{"audioDevices":"[{\"id\":\"{0.0.0.00000000}.{0a8da4ba-891f-4c4a-bb04-db45c4c4216b}\",\"name\":\"Casque pour téléphone (Arctis 5 Chat)\",\"iconPath\":\"%windir%\\\\system32\\\\mmres.dll\",\"iconID\":-3015,\"isActive\":false},{\"id\":\"{0.0.0.00000000}.{3303b7b7-cabf-419a-ae1e-8f7ea41d4de1}\",\"name\":\"Haut-parleurs (High Definition Audio Device)\",\"iconPath\":\"%windir%\\\\system32\\\\mmres.dll\",\"iconID\":-3010,\"isActive\":true,\"hotKey\":{\"keyCode\":\"digit1\",\"modifiers\":[\"shift\",\"control\"],\"identifier\":\"c81282b2-3d80-497d-8678-d0eda30f68e1\",\"scope\":\"system\"}},{\"id\":\"{0.0.0.00000000}.{ff05fbfb-685e-44eb-b415-6fd6036f03b4}\",\"name\":\"Casque (Arctis 5 Game)\",\"iconPath\":\"%windir%\\\\system32\\\\mmres.dll\",\"iconID\":-3031,\"isActive\":false}]"}